mrio/__init__.py
mrio/chunk_reader.py
mrio/earthengine_api.py
mrio/env_options.py
mrio/errors.py
mrio/fields.py
mrio/protocol.py
mrio/readers.py
mrio/slice_transformer.py
mrio/temporal_utils.py
mrio/type_definitions.py
mrio/validators.py
mrio/writers.py
mrio-0.1.6.dist-info/LICENSE
mrio-0.1.6.dist-info/METADATA
mrio-0.1.6.dist-info/WHEEL
mrio-0.1.6.dist-info/RECORD
