Metadata-Version: 2.1
Name: mrio
Version: 0.1.6
Summary: Python Package that support the read/write of multidimensional COG files
Home-page: https://github.com/tacofoundation/mrio-python
Author: Cesar Aybar
Author-email: cesar.aybar@uv.es
Requires-Python: >=3.10,<4.0
Classifier: Programming Language :: Python :: 3
Classifier: Programming Language :: Python :: 3.10
Classifier: Programming Language :: Python :: 3.11
Classifier: Programming Language :: Python :: 3.12
Requires-Dist: einops (>=0.8.0)
Requires-Dist: rasterio (>=1.4.3)
Requires-Dist: typing-extensions (>=4.12.2)
Project-URL: Documentation, https://tacofoundation.github.io/mrio/
Project-URL: Repository, https://github.com/tacofoundation/mrio-python
